flyvis/__init__.py
flyvis/solver.py
flyvis/version.py
flyvis/analysis/__init__.py
flyvis/analysis/__main__.ipynb
flyvis/analysis/__main_per_model__.ipynb
flyvis/analysis/clustering.py
flyvis/analysis/correlation.py
flyvis/analysis/flash_responses.py
flyvis/analysis/moving_bar_responses.py
flyvis/analysis/moving_edge_currents.py
flyvis/analysis/optimal_stimuli.py
flyvis/analysis/stimulus_responses.py
flyvis/analysis/stimulus_responses_currents.py
flyvis/analysis/validation.py
flyvis/analysis/animations/__init__.py
flyvis/analysis/animations/activations.py
flyvis/analysis/animations/animations.py
flyvis/analysis/animations/hexflow.py
flyvis/analysis/animations/hexscatter.py
flyvis/analysis/animations/imshow.py
flyvis/analysis/animations/network.py
flyvis/analysis/animations/sintel.py
flyvis/analysis/animations/traces.py
flyvis/analysis/visualization/__init__.py
flyvis/analysis/visualization/figsize_utils.py
flyvis/analysis/visualization/matplotlibrc
flyvis/analysis/visualization/network_fig.py
flyvis/analysis/visualization/plots.py
flyvis/analysis/visualization/plt_utils.py
flyvis/config/solver.yaml
flyvis/config/network/network.yaml
flyvis/config/network/connectome/connectome.yaml
flyvis/config/network/dynamics/dynamics.yaml
flyvis/config/network/edge_config/edge_config.yaml
flyvis/config/network/edge_config/sign/sign.yaml
flyvis/config/network/edge_config/syn_count/syn_count.yaml
flyvis/config/network/edge_config/syn_strength/syn_strength.yaml
flyvis/config/network/node_config/node_config.yaml
flyvis/config/network/node_config/bias/bias.yaml
flyvis/config/network/node_config/time_const/time_const.yaml
flyvis/config/network/stimulus_config/stimulus_config.yaml
flyvis/config/optim/optim.yaml
flyvis/config/penalizer/penalizer.yaml
flyvis/config/scheduler/scheduler.yaml
flyvis/config/task/task.yaml
flyvis/connectome/__init__.py
flyvis/connectome/connectome.py
flyvis/connectome/fib25-fib19_v2.2.json
flyvis/datasets/__init__.py
flyvis/datasets/datasets.py
flyvis-1.1.2.dist-info/METADATA
flyvis-1.1.2.dist-info/WHEEL
flyvis-1.1.2.dist-info/entry_points.txt
flyvis-1.1.2.dist-info/top_level.txt
flyvis-1.1.2.dist-info/RECORD
