Metadata-Version: 2.1
Name: flyvis
Version: 1.1.2
Summary: Connectome and task-constrained vision models of the fruit fly.
Project-URL: Homepage, https://github.com/TuragaLab/flyvis
Project-URL: Documentation, https://turagalab.github.io/flyvis
Project-URL: Source Code, https://github.com/TuragaLab/flyvis
Project-URL: Bug Tracker, https://github.com/TuragaLab/flyvis/issues
Classifier: Intended Audience :: Developers
Classifier: Intended Audience :: Education
Classifier: Intended Audience :: Science/Research
Classifier: Topic :: Adaptive Technologies
Classifier: Topic :: Scientific/Engineering
Classifier: Topic :: Scientific/Engineering :: Artificial Intelligence
Classifier: Topic :: Scientific/Engineering :: Mathematics
Classifier: License :: OSI Approved :: MIT License
Classifier: Natural Language :: English
Classifier: Operating System :: OS Independent
Classifier: Programming Language :: Python :: 3
Classifier: Development Status :: 3 - Alpha
Requires-Python: <3.13,>=3.9
Requires-Dist: ipython
Requires-Dist: numba
Requires-Dist: datamate
Requires-Dist: scipy
Requires-Dist: matplotlib
Requires-Dist: networkx
Requires-Dist: scikit-learn
Requires-Dist: umap-learn
Requires-Dist: ffmpeg-python
Requires-Dist: pytest
Requires-Dist: torch
Requires-Dist: torchvision
Requires-Dist: python-dotenv
Requires-Dist: hydra-core
Requires-Dist: toolz
Requires-Dist: tqdm
Requires-Dist: requests
Requires-Dist: google-api-python-client
Requires-Dist: xarray
Requires-Dist: pandas
Requires-Dist: joblib
Requires-Dist: colorama
Provides-Extra: dev
Requires-Dist: pre-commit; extra == "dev"
Requires-Dist: ruff; extra == "dev"
Requires-Dist: pytest; extra == "dev"
Requires-Dist: pytest-cov; extra == "dev"
Requires-Dist: jupyter; extra == "dev"
Requires-Dist: papermill; extra == "dev"
Requires-Dist: tabulate; extra == "dev"
Requires-Dist: tqdm; extra == "dev"
Requires-Dist: ipywidgets; extra == "dev"
Provides-Extra: docs
Requires-Dist: mkdocs; extra == "docs"
Requires-Dist: mkdocs-material; extra == "docs"
Requires-Dist: markdown-include; extra == "docs"
Requires-Dist: mkdocs-redirects; extra == "docs"
Requires-Dist: mkdocstrings[python]>=0.18; extra == "docs"
Requires-Dist: nbconvert; extra == "docs"
Requires-Dist: mike; extra == "docs"
Requires-Dist: mkdocs-macros-plugin; extra == "docs"
Requires-Dist: jupyter; extra == "docs"
Requires-Dist: tabulate; extra == "docs"
Requires-Dist: tqdm; extra == "docs"
Requires-Dist: ipywidgets; extra == "docs"
Provides-Extra: examples
Requires-Dist: jupyter; extra == "examples"
Requires-Dist: tabulate; extra == "examples"
Requires-Dist: tqdm; extra == "examples"
Requires-Dist: ipywidgets; extra == "examples"
Provides-Extra: pretrained
Requires-Dist: numba==0.55.2; extra == "pretrained"
Requires-Dist: matplotlib==3.7.1; extra == "pretrained"
Requires-Dist: scikit-learn==1.1.1; extra == "pretrained"
Requires-Dist: umap-learn==0.5.3; extra == "pretrained"
Requires-Dist: xarray==2023.7.0; extra == "pretrained"
Requires-Dist: pandas==2.2.2; extra == "pretrained"
Requires-Dist: joblib==1.3.2; extra == "pretrained"
